backStrategy/__init__.py
backStrategy/main.py
backStrategy/engine/__init__.py
backStrategy/engine/backEngine.py
backStrategy/engine/template.py
backStrategy/strategy/__init__.py
backStrategy/strategy/test_demo.py
backStrategy/utils/__init__.py
backStrategy-0.1.0.3.dist-info/LICENSE
backStrategy-0.1.0.3.dist-info/METADATA
backStrategy-0.1.0.3.dist-info/WHEEL
backStrategy-0.1.0.3.dist-info/top_level.txt
backStrategy-0.1.0.3.dist-info/RECORD
